chrori/__init__.py
chrori/haplocall.py
chrori/mergevcf.py
chrori/mkvcf.py
chrori/params.py
chrori/refindex.py
chrori/selectvariants.py
chrori/utils.py
chrori/visualize.py
chrori-0.0.1.dist-info/LICENSE
chrori-0.0.1.dist-info/METADATA
chrori-0.0.1.dist-info/WHEEL
chrori-0.0.1.dist-info/entry_points.txt
chrori-0.0.1.dist-info/top_level.txt
chrori-0.0.1.dist-info/RECORD
